test_mcp/__init__.py
test_mcp_dongkoo-0.4.0.dist-info/METADATA
test_mcp_dongkoo-0.4.0.dist-info/WHEEL
test_mcp_dongkoo-0.4.0.dist-info/entry_points.txt
test_mcp_dongkoo-0.4.0.dist-info/RECORD
