Metadata-Version: 2.4
Name: test-mcp-dongkoo
Version: 0.4.0
Summary: A simple MCP server with basic tools
Project-URL: Homepage, https://github.com/dongkoo/test-mcp
Project-URL: Repository, https://github.com/dongkoo/test-mcp.git
Project-URL: Issues, https://github.com/dongkoo/test-mcp/issues
Project-URL: Documentation, https://github.com/dongkoo/test-mcp#readme
Author-email: DongKoo Kim <dongkoo@example.com>
Maintainer-email: DongKoo Kim <dongkoo@example.com>
License-Expression: MIT
Keywords: anthropic,claude,mcp,server,tools
Classifier: Development Status :: 3 - Alpha
Classifier: Intended Audience :: Developers
Classifier: License :: OSI Approved :: MIT License
Classifier: Programming Language :: Python :: 3
Classifier: Programming Language :: Python :: 3.11
Classifier: Programming Language :: Python :: 3.12
Classifier: Topic :: Software Development :: Libraries :: Python Modules
Requires-Python: >=3.11
Requires-Dist: mcp[cli]>=1.13.1
Provides-Extra: dev
Requires-Dist: black>=22.0; extra == 'dev'
Requires-Dist: pytest>=7.0; extra == 'dev'
Requires-Dist: ruff>=0.1.0; extra == 'dev'
